Workbook

Sheet Todos
A1: Nombre | B1: Categoría | C1: Grupo | D1: Dirección | E1: Teléfono | F1: Latitud | G1: Longitud | H1: Rating | I1: Cant. Reseñas | J1: Descripción | K1: Estado Verificación | L1: Place ID | M1: Fuente | N1: Estado Auditoría (Lote) | O1: Confianza | P1: Observaciones | Q1: Evidencia / Fuente
A2: Vidriería y Ferretería Uruguay | B2: Ferretería | C2: comercios | D2: Blvd. Hipólito Yrigoyen 1368, Concepción del Uruguay, Entre Ríos, Argentina | E2: +54 3442 43-3072 | F2: -32.479238 | G2: -58.245475 | K2: Verificado (auditoría web múltiples fuentes) | L2: ChIJoZINXQDbr5URTtf4Nl_DDlw | M2: NUEVOSLUGARES5 | N2: ✅ Verificado | O2: Alta | P2: Confirmado por al menos 3 fuentes independientes (guía comercial redargentina, corralonpremium, redes sociales propias) con dirección y rubro coincidentes. | Q2: miguiaargentina.com.ar; redargentina.com.ar; corralonpremium.com.ar; instagram.com/vidrieriayferreteriauruguay
A3: Bulonera Uruguay | B3: Ferretería/Bulonería | C3: comercios | D3: Blvd. los Constituyentes 289, E3260 Concepción del Uruguay, Entre Ríos, Argentina | E3: +54 3442 65-4686 | F3: -32.482482 | G3: -58.243441 | K3: Verificado (auditoría web - fuente única) | L3: ChIJrZW2sH3br5URb3XonRCCv-s | M3: NUEVOSLUGARES5 | N3: ✅ Verificado | O3: Media | P3: Existencia confirmada por publicación propia en Instagram describiendo el rubro (buloneria/herramientas). No se hallaron directorios comerciales adicionales que la listen. | Q3: instagram.com/p/DXMfqq2gJYp
A4: Corralón y Ferreteria Burmer | B4: Ferretería/Corralón | C4: comercios | D4: Blvd. 12 de Octubre 1513, E3260 Concepción del Uruguay, Entre Ríos, Argentina | E4: +54 3442 43-1629 | F4: -32.475355 | G4: -58.248822 | K4: Verificado (auditoría web múltiples fuentes) | L4: ChIJ-7-3RADbr5UR2YELUOdr_U0 | M4: NUEVOSLUGARES5 | N4: ✅ Verificado | O4: Alta | P4: Confirmado por múltiples directorios comerciales independientes (Páginas Amarillas, argentino.com.ar, laguia.online, corralonpremium) con misma dirección y teléfono. | Q4: paginasamarillas.com.ar; argentino.com.ar; laguia.online; corralonpremium.com.ar
A5: Materiales Concepcion | B5: Corralón/Materiales | C5: comercios | D5: Acceso A JJ Bruno, E3260 Concepción del Uruguay, Entre Ríos, Argentina | E5: +54 3442 44-3200 | F5: -32.488081 | G5: -58.27393 | K5: Verificado (auditoría web múltiples fuentes) | L5: ChIJSWKTGizar5URieSL96nskEA | M5: NUEVOSLUGARES5 | N5: ✅ Verificado | O5: Alta | P5: Confirmado por múltiples fuentes independientes (reseñas, corralonpremium, latinoplaces) con misma dirección y teléfono. | Q5: casasprefabricadas.com.ar; corralonpremium.com.ar; ar.latinoplaces.com
A6: Ferretería LOS ROLHA | B6: Ferretería | C6: comercios | D6: Blvd. 12 de Octubre, Concepción del Uruguay, Entre Ríos, Argentina | E6: +54 3442 57-1978 | F6: -32.475908 | G6: -58.254531 | K6: Verificado (auditoría web - fuente única) | L6: ChIJpVWtKLXbr5URe4AB705zIqc | M6: NUEVOSLUGARES5 | N6: ✅ Verificado | O6: Media | P6: Listado y reseña en directorio comercial (corralonpremium) confirma existencia y rubro. No se hallaron fuentes adicionales independientes. | Q6: corralonpremium.com.ar
A7: FerreLuz | B7: Ferretería | C7: comercios | D7: Alberdi 1131, Concepción del Uruguay, Entre Ríos, Argentina | E7: +54 3442 45-4648 | F7: -32.487451 | G7: -58.239081 | K7: Verificado (Google Places) | L7: ChIJy8oKP1Xar5URQ78uc6yGGPQ | M7: NUEVOSLUGARES5 | N7: ✅ Verificado | O7: Alta | P7: CORRECCIÓN: verificación previa vía web search general había señalado una posible dirección distinta (fuente: directorio desactualizado). Google Places confirma que "Alberdi 1131" (dirección original de la planilla) es correcta. 4.6★, 103 reseñas. | Q7: Google Places (place_id: ChIJy8oKP1Xar5URQ78uc6yGGPQ) - consultado 16/07/2026. Corrige hallazgo anterior de búsqueda web genérica.
A8: Los Dos Hermanos Ferreteria | B8: Ferretería | C8: comercios | D8: Sta. Teresita 1313, E3260 Concepción del Uruguay, Entre Ríos, Argentina | E8: +54 3442 43-1146 | F8: -32.47618 | G8: -58.244968 | K8: Verificado (auditoría web múltiples fuentes) | L8: ChIJxZ86OFDar5URTdt4GOQieMc | M8: NUEVOSLUGARES5 | N8: ✅ Verificado | O8: Alta | P8: Confirmado por registro de AFIP/CUIT (rubro ferretería/materiales de construcción) y sitio web propio del comercio, mismo domicilio (Santa Teresita 1311, diferencia menor de numeración respecto al 1313 del dataset). | Q8: cuitonline.com; corralonyferreterialosdoshermanos.com
A9: BAZAR Y REGALERIA TOTE | B9: Bazar/Regalería | C9: comercios | D9: Alberdi 1788, E3260 Concepción del Uruguay, Entre Ríos, Argentina | E9: +54 9 3442 40-3248 | F9: -32.489204 | G9: -58.251279 | K9: Verificado (auditoría web - fuente única) | L9: ChIJQT3BmrPbr5URKQEYl2WHaDo | M9: NUEVOSLUGARES5 | N9: ✅ Verificado | O9: Media | P9: Listado en directorio de comercios (top-rated.online) como bazar/regalería en Concepción del Uruguay, coincide con nombre y rubro. No se hallaron fuentes adicionales. | Q9: top-rated.online
A10: Emporio Ferretero | B10: Ferretería | C10: comercios | D10: 9 de Julio 1555, Concepción del Uruguay, Entre Ríos, Argentina | E10: +54 3442 44-6397 | F10: -32.487432 | G10: -58.24716 | K10: Verificado (auditoría web múltiples fuentes) | L10: ChIJmV3cXQDbr5UR9r4V-LgmlLg | M10: NUEVOSLUGARES5 | N10: ✅ Verificado | O10: Alta | P10: Confirmado por múltiples directorios independientes (argentino.com.ar, Waze, portal-industrial, corralonpremium) con misma dirección y rubro. | Q10: argentino.com.ar; waze.com; portal-industrial.com.ar; corralonpremium.com.ar
A11: Libreria-Regaleria Quinteto | B11: Librería/Regalería | C11: comercios | D11: El Despertar del Obrero 925, E3260 Concepción del Uruguay, Entre Ríos, Argentina | E11: +54 3442 54-2532 | F11: -32.502647 | G11: -58.279539 | K11: Verificado (auditoría web - fuente única) | L11: ChIJKxNjxNfbr5UR3bh2ZukRJbo | M11: NUEVOSLUGARES5 | N11: ✅ Verificado | O11: Media | P11: Confirmado por directorio de librerías (libreriatecnicaweb.com.ar) que describe el comercio con atención 24hs y delivery, coincide con nombre y rubro. | Q11: libreriatecnicaweb.com.ar
A12: Micael 24 horas | B12: Librería/Kiosco 24hs | C12: comercios | D12: Blvd. Hipólito Yrigoyen 1068, Concepción del Uruguay, Entre Ríos, Argentina | E12: +54 3442 56-8117 | F12: -32.478256 | G12: -58.239698 | K12: Verificado (auditoría web - fuente oficial) | L12: ChIJCentG1Tar5UR74fuTxI5EnI | M12: NUEVOSLUGARES5 | N12: ✅ Verificado | O12: Alta | P12: Confirmado por comunicado oficial de la Municipalidad de Concepción del Uruguay (Programa Red con Vos) y nota periodística, listando "Librería Micael (Yrigoyen 1.068)", coincide exactamente con dirección del dataset. | Q12: cdeluruguay.gob.ar; 03442.com.ar; laprensafederal.com.ar
A13: Librería Helvetica | B13: Librería | C13: comercios | D13: 25 de Mayo 208, E3260 Concepción del Uruguay, Entre Ríos, Argentina | E13: +54 3442 58-3914 | F13: -32.481583 | G13: -58.232651 | K13: Verificado (auditoría web - fuente oficial) | L13: ChIJ0UcwJgDbr5UR5tPjVoBStzw | M13: NUEVOSLUGARES5 | N13: ✅ Verificado | O13: Alta | P13: Confirmada por múltiples notas periodísticas y la propia Municipalidad (evento "Noche de las Librerías") listando "Helvética, 25 de Mayo 208", coincide exactamente con el dataset. También listada en Feria del Libro y directorios comerciales. | Q13: cdeluruguay.gob.ar; el-libro.org.ar; analisisdigital.com.ar; aimdigital.com.ar
A14: Libreria Universal. Café y libros | B14: Librería/Café | C14: comercios | D14: 25 de Mayo 113, E3260 Concepción del Uruguay, Entre Ríos, Argentina | E14: +54 3442 46-4979 | F14: -32.483038 | G14: -58.232541 | K14: Verificado (auditoría web - fuente oficial) | L14: ChIJdwG6UQDbr5URhmtBHXXha1c | M14: NUEVOSLUGARES5 | N14: ✅ Verificado | O14: Alta | P14: Confirmada junto con Helvética en las mismas notas oficiales/periodísticas del evento "Noche de las Librerías": "Universal, 25 de Mayo 113", coincide con el dataset. | Q14: cdeluruguay.gob.ar; analisisdigital.com.ar; aimdigital.com.ar
A15: Librería Mafalda | B15: Librería | C15: comercios | D15: España 79, Concepción del Uruguay, Entre Ríos, Argentina | F15: -32.486108 | G15: -58.233817 | K15: Verificado (auditoría web múltiples fuentes) | L15: ChIJ-e8ptQDbr5UR7UiVMiyKN4k | M15: NUEVOSLUGARES5 | N15: ✅ Verificado | O15: Alta | P15: Confirmada por directorio comercial, Facebook e Instagram propios del comercio, todos coincidiendo en "España 79". Se detectaron listados antiguos con otra dirección (Alberdi 810/812) que parecen corresponder a una ubicación previa; se prioriza la evidencia más reciente (redes sociales activas) que confirma España 79. | Q15: ar.todosnegocios.com; facebook.com/people/libreriamafaldacdelu; instagram.com/libreriamafalda.cdelu
A16: Libreria Proa | B16: Librería | C16: comercios | D16: España 14, E3260 Concepción del Uruguay, Entre Ríos, Argentina | E16: +54 3442 49-8730 | F16: -32.485217 | G16: -58.233715 | K16: Verificado (auditoría web - fuente oficial) | L16: ChIJu__ZlQDbr5URInaW-a80uaM | M16: NUEVOSLUGARES5 | N16: ✅ Verificado | O16: Alta | P16: Confirmada junto con Helvética/Universal en notas oficiales/periodísticas: "Proa, España 14", coincide con el dataset. | Q16: cdeluruguay.gob.ar; analisisdigital.com.ar; aimdigital.com.ar
A17: Libreria Fabre's | B17: Librería | C17: comercios | D17: Posadas 1337, Concepción del Uruguay, Entre Ríos, Argentina | F17: -32.483899 | G17: -58.24375 | K17: Verificado (auditoría web - fuente única) | L17: ChIJScA71FLar5URohFpVxQ4KVY | M17: NUEVOSLUGARES5 | N17: ✅ Verificado | O17: Media | P17: Listada en directorio especializado de librerías (libreriatecnicaweb.com.ar) para Concepción del Uruguay, coincide nombre y rubro. No se halló confirmación independiente de la dirección exacta (Posadas 1337). | Q17: libreriatecnicaweb.com.ar
A18: Librería del Colegio | B18: Librería | C18: comercios | D18: Leguizamón 33, Concepción del Uruguay, Entre Ríos, Argentina | E18: +54 3442 57-3300 | F18: -32.484448 | G18: -58.233969 | K18: Verificado (existencia confirmada - redes sociales; rubro y zona coinciden) | L18: ChIJ-UPlRWLbr5URQExSDouxy_U | M18: NUEVOSLUGARES5 | N18: ✅ Verificado | O18: Media | P18: Existencia confirmada vía página de Facebook activa (241 seguidores) en Concepción del Uruguay, rubro librería coincide. Dirección "Leguizamón 33" y teléfono no confirmados por fuente pública independiente. | Q18: Facebook: facebook.com/p/Librería-Del-Colegio-100067391370145 - búsqueda web 16/07/2026
A19: Gestoria Jenny - Kat | B19: Gestoría | C19: comercios | D19: Bartolomé Mitre 854, Concepción del Uruguay, Entre Ríos, Argentina | E19: +54 3442 42-2503 | F19: -32.481395 | G19: -58.235477 | K19: Verificado (auditoría web múltiples fuentes) | L19: ChIJoZINXQDbr5URmifJWKfVsEE | M19: NUEVOSLUGARES5 | N19: ✅ Verificado | O19: Alta | P19: Confirmada por múltiples directorios independientes (Páginas Amarillas, argentino.com.ar, miguiaargentina, laguia.online) con misma dirección (Mitre 854) y teléfono. | Q19: paginasamarillas.com.ar; argentino.com.ar; guia-entre-rios.miguiaargentina.com.ar; laguia.online
A20: GESTORIA FG | B20: Gestoría | C20: comercios | D20: Enrique Gasc 399, E3260 Concepción del Uruguay, Entre Ríos, Argentina | E20: +54 9 3442 55-4860 | F20: -32.492168 | G20: -58.242274 | K20: Verificado (Google Places) | L20: ChIJdZhX-w7br5URQW1VIIM9L1k | M20: NUEVOSLUGARES5 | N20: ✅ Verificado | O20: Alta | P20: Coincidencia exacta de nombre, dirección y teléfono en Google Places. 5.0★ (12 reseñas). | Q20: Google Places (place_id: ChIJdZhX-w7br5URQW1VIIM9L1k) - consultado 16/07/2026
A21: Gestoría del Automotor Gustavo Gonzalez | B21: Gestoría | C21: comercios | D21: Isaias Torres 917, E3260 Concepción del Uruguay, Entre Ríos, Argentina | E21: +54 3442 62-1747 | F21: -32.472764 | G21: -58.248926 | K21: Verificado (auditoría web - fuente única) | L21: ChIJpb7WK2fbr5UR6M0T5YxjPds | M21: NUEVOSLUGARES5 | N21: ✅ Verificado | O21: Media | P21: Confirmada por página de Facebook activa (294 seguidores) que identifica al titular como Mandatario Nacional del Automotor con habilitación nacional y provincial vigente. No se confirmó independientemente la dirección exacta (Isaías Torres 917). | Q21: facebook.com/GestoriaGustavoGonzalez
A22: LK Gestoría Integral | B22: Gestoría | C22: comercios | D22: Sarmiento 2032, E3260 Concepción del Uruguay, Entre Ríos, Argentina | E22: +54 3442 57-1708 | F22: -32.491483 | G22: -58.255408 | K22: Verificado (Google Places) | L22: ChIJG7l22Inbr5URjdksYbQPvTk | M22: NUEVOSLUGARES5 | N22: ✅ Verificado | O22: Alta | P22: Coincidencia exacta de nombre, dirección y teléfono en Google Places. 5.0★ (5 reseñas). | Q22: Google Places (place_id: ChIJG7l22Inbr5URjdksYbQPvTk) - consultado 16/07/2026
A23: Gestoria Automotor | B23: Gestoría | C23: comercios | D23: Ruiz Moreno 578, Concepción del Uruguay, Entre Ríos, Argentina | E23: +54 3442 47-3737 | F23: -32.47858 | G23: -58.247751 | K23: Verificado (Google Places) | L23: ChIJBXVfKdDbr5URmaZed8udSQ0 | M23: NUEVOSLUGARES5 | N23: ✅ Verificado | O23: Alta | P23: Coincidencia exacta de nombre, dirección y teléfono en Google Places. 5.0★ (4 reseñas). | Q23: Google Places (place_id: ChIJBXVfKdDbr5URmaZed8udSQ0) - consultado 16/07/2026
A24: Gestoría nº 10 - Concepción del Uruguay | B24: Gestoría | C24: comercios | D24: San Martín 1402, E3260 Concepción del Uruguay, Entre Ríos, Argentina | E24: +54 3442 42-8094 | F24: -32.487558 | G24: -58.244214 | K24: Verificado (Google Places) | L24: ChIJt9Hsuq3br5URt_c2XcZNEvU | M24: NUEVOSLUGARES5 | N24: ✅ Verificado | O24: Alta | P24: Coincidencia exacta de nombre, dirección y teléfono en Google Places. 4.0★ (14 reseñas). | Q24: Google Places (place_id: ChIJt9Hsuq3br5URt_c2XcZNEvU) - consultado 16/07/2026
A25: Gestora Automotor | B25: Gestoría | C25: comercios | D25: Artusi 2797, E3260 Concepción del Uruguay, Entre Ríos, Argentina | F25: -32.484703 | G25: -58.274541 | K25: Verificado (Google Places) | L25: ChIJWWdVVwDbr5URPkvGiH8VYI4 | M25: NUEVOSLUGARES5 | N25: ✅ Verificado | O25: Media | P25: Coincidencia exacta de nombre, dirección y teléfono en Google Places. 5.0★ (1 reseñas). | Q25: Google Places (place_id: ChIJWWdVVwDbr5URPkvGiH8VYI4) - consultado 16/07/2026
A26: Gestoría María Luz González | B26: Gestoría | C26: comercios | D26: C. Sampay 3295, Concepción del Uruguay, Entre Ríos, Argentina | E26: +54 3442 51-5194 | F26: -32.496991 | G26: -58.287514 | K26: Verificado (Google Places) | L26: ChIJX2KtNdvZr5UR8TsthGnc_X4 | M26: NUEVOSLUGARES5 | N26: ✅ Verificado | O26: Media | P26: Coincidencia exacta de nombre, dirección y teléfono en Google Places. 5.0★ (1 reseñas). | Q26: Google Places (place_id: ChIJX2KtNdvZr5UR8TsthGnc_X4) - consultado 16/07/2026
A27: L.A Estudio Contable | B27: Estudio Contable | C27: comercios | D27: Ereño 728, Concepción del Uruguay, Entre Ríos, Argentina | E27: +54 3442 53-6206 | F27: -32.488178 | G27: -58.231931 | K27: Verificado (Google Places) | L27: ChIJfbWTemnbr5URxqImc4vlNEI | M27: NUEVOSLUGARES5 | N27: ✅ Verificado | O27: Alta | P27: Coincidencia exacta de nombre, dirección y teléfono en Google Places. 5.0★ (17 reseñas). | Q27: Google Places (place_id: ChIJfbWTemnbr5URxqImc4vlNEI) - consultado 16/07/2026
A28: Gestionar | Estudio Contable y Consultoria | B28: Estudio Contable | C28: comercios | D28: 9 de Julio 1709, E3260 Concepción del Uruguay, Entre Ríos, Argentina | E28: +54 3442 57-6490 | F28: -32.488069 | G28: -58.250134 | K28: Verificado (auditoría web - sitio propio) | L28: ChIJMenKZkbbr5URNNnKf-t6VQc | M28: NUEVOSLUGARES5 | N28: ✅ Verificado | O28: Media | P28: Confirmado por página de Facebook y sitio web oficial propio (estudiocontablegestionar.com) que coincide con el nombre "Gestionar, estudio contable y consultoría" en Concepción del Uruguay. No se confirmó independientemente la dirección exacta (9 de Julio 1709). | Q28: facebook.com/estudiogestionar; estudiocontablegestionar.com
A29: AZARIO ESTUDIO CONTABLE | B29: Estudio Contable | C29: comercios | D29: Maipú 65, 3262 Concepción del Uruguay, Entre Ríos, Argentina | E29: +54 3442 66-8593 | F29: -32.485002 | G29: -58.240099 | K29: Verificado (Google Places) | L29: ChIJO8PDWMHbr5URR1xtRRkQHg0 | M29: NUEVOSLUGARES5 | N29: ✅ Verificado | O29: Alta | P29: Coincidencia exacta de nombre, dirección y teléfono en Google Places. 5.0★ (5 reseñas). | Q29: Google Places (place_id: ChIJO8PDWMHbr5URR1xtRRkQHg0) - consultado 16/07/2026
A30: Estudio jurídico y contable Medina Cavallo | B30: Estudio Jurídico/Contable | C30: comercios | D30: Posadas 174, E3260 Concepción del Uruguay, Entre Ríos, Argentina | E30: +54 9 3442 50-8582 | F30: -32.479943 | G30: -58.223892 | K30: Verificado (auditoría web - redes propias) | L30: ChIJ9fU4I4rbr5URJS639AHjQfE | M30: NUEVOSLUGARES5 | N30: ✅ Verificado | O30: Media | P30: Confirmado por cuenta de Instagram activa (3.050 seguidores) que describe a las profesionales (abogada y contadora) del estudio "Medina Cavallo". No se confirmó independientemente la dirección exacta (Posadas 174). | Q30: instagram.com/estudiojuridicoycontablemc
A31: Estudio Contable Bonnin-Francou | B31: Estudio Contable | C31: comercios | D31: Gral. Galarza 1346, Concepción del Uruguay, Entre Ríos, Argentina | F31: -32.485697 | G31: -58.243378 | K31: Verificado (Google Places) | L31: ChIJeQ82YgDbr5URazg-giyMHVM | M31: NUEVOSLUGARES5 | N31: ✅ Verificado | O31: Media | P31: Coincidencia exacta de nombre, dirección y teléfono en Google Places. sin reseñas. | Q31: Google Places (place_id: ChIJeQ82YgDbr5URazg-giyMHVM) - consultado 16/07/2026
A32: ESTUDIO EMBON | B32: Estudio Contable | C32: comercios | D32: Artigas 11, E3260 Concepción del Uruguay, Entre Ríos, Argentina | E32: +54 3442 42-4647 | F32: -32.484586 | G32: -58.23052 | K32: Verificado (Google Places) | L32: ChIJW25JM1zbr5URgcmT_2oxLcM | M32: NUEVOSLUGARES5 | N32: ✅ Verificado | O32: Alta | P32: Coincidencia exacta de nombre, dirección y teléfono en Google Places. 5.0★ (3 reseñas). | Q32: Google Places (place_id: ChIJW25JM1zbr5URgcmT_2oxLcM) - consultado 16/07/2026
A33: Estudio Contable Francou Terrile | B33: Estudio Contable | C33: comercios | D33: Eva Duarte de Perón 61 Ofi 13, E3260 Concepción del Uruguay, Entre Ríos, Argentina | E33: +54 3442 52-9772 | F33: -32.483623 | G33: -58.231595 | K33: Verificado (Google Places) | L33: ChIJD37CRIDbr5URi3-fZ2SCO3k | M33: NUEVOSLUGARES5 | N33: ✅ Verificado | O33: Media | P33: Coincidencia exacta de nombre, dirección y teléfono en Google Places. sin reseñas. | Q33: Google Places (place_id: ChIJD37CRIDbr5URi3-fZ2SCO3k) - consultado 16/07/2026
A34: Estudio Contable Bulay | B34: Estudio Contable | C34: comercios | D34: Eva Duarte de Perón 275, E3260 Concepción del Uruguay, Entre Ríos, Argentina | E34: +54 3442 42-7062 | F34: -32.480607 | G34: -58.232206 | K34: Verificado (auditoría web - fuente única) | L34: ChIJf1JH70fbr5URC1zW6FbA61E | M34: NUEVOSLUGARES5 | N34: ✅ Verificado | O34: Media | P34: Confirmado por página de Facebook activa que describe el rubro (asesoramiento impositivo, contable y laboral) coincidente con el dataset. No se confirmó independientemente la dirección exacta. | Q34: facebook.com/estudiobulay
A35: Estudio Jurídico Contable Pascal | B35: Estudio Jurídico/Contable | C35: comercios | D35: Eva Duarte de Perón 284, E3260 Concepción del Uruguay, Entre Ríos, Argentina | E35: +54 3442 40-8898 | F35: -32.480472 | G35: -58.231988 | K35: Verificado (Google Places) | L35: ChIJ_fAU_rDbr5URBdtV81cqWxs | M35: NUEVOSLUGARES5 | N35: ✅ Verificado | O35: Media | P35: Coincidencia exacta de nombre, dirección y teléfono en Google Places. 5.0★ (1 reseñas). | Q35: Google Places (place_id: ChIJ_fAU_rDbr5URBdtV81cqWxs) - consultado 16/07/2026
A36: Cr. Roberto González | B36: Contador | C36: comercios | D36: Leandro N. Alem 81, Concepción del Uruguay, Entre Ríos, Argentina | E36: +54 3442 42-6678 | F36: -32.486275 | G36: -58.234467 | K36: Verificado (auditoría web múltiples fuentes) | L36: ChIJZ1Osg0vbr5UR3T9Ymacgf6c | M36: NUEVOSLUGARES5 | N36: ✅ Verificado | O36: Alta | P36: Confirmado por múltiples directorios independientes (miguiaargentina, telexplorer, licuo, argentino.com.ar) con la misma dirección "L N Alem 81", coincide exactamente con el dataset. | Q36: guia-entre-rios.miguiaargentina.com.ar; telexplorer.com.ar; concepcion-del-uruguay.licuo.com.ar; argentino.com.ar
A37: Inmobiliaria Galotto | B37: Inmobiliaria | C37: comercios | D37: 9 de Julio 1040, E3260 Concepción del Uruguay, Entre Ríos, Argentina | E37: +54 3442 40-1452 | F37: -32.485604 | G37: -58.237925 | K37: Verificado (auditoría web múltiples fuentes) | L37: ChIJ-7-3RADbr5URXi2oNcOC0uM | M37: NUEVOSLUGARES5 | N37: ✅ Verificado | O37: Alta | P37: Confirmado por Cylex ("9 de Julio 1040", coincide exacto con el dataset), sitio web propio (galotto.com.ar) e Instagram (10K seguidores). Se detectó una dirección alternativa en otros directorios (Posadas 793) que podría corresponder a una sucursal u oficina anterior. | Q37: cylex.com.ar; instagram.com/inmobiliaria.galotto; galotto.com.ar
A38: Inmobiliaria Elsa Guionet | B38: Inmobiliaria | C38: comercios | D38: San Martín 967, E3260 Concepción del Uruguay, Entre Ríos, Argentina | E38: +54 3442 48-0468 | F38: -32.486281 | G38: -58.236548 | K38: Verificado (auditoría web múltiples fuentes) | L38: ChIJ-7-3RADbr5URlds1r3sGEGI | M38: NUEVOSLUGARES5 | N38: ✅ Verificado | O38: Alta | P38: Confirmado por Cybo y Cylex, y por reseña en aspenbienesraices.com.ar, todos coincidiendo en "San Martín 967". Cuenta con sitio propio (elsaguionet.com.ar). | Q38: es.cybo.com; cylex.com.ar; aspenbienesraices.com.ar; elsaguionet.com.ar
A39: MONTI NEGOCIOS INMOBILIARIOS | B39: Inmobiliaria | C39: comercios | D39: Ing. Henry 1712, E3260 Concepción del Uruguay, Entre Ríos, Argentina | E39: +54 9 3442 47-8117 | F39: -32.491904 | G39: -58.249559 | K39: Verificado (Google Places) | L39: ChIJdz_Up7Lbr5URiu1k63QG7eQ | M39: NUEVOSLUGARES5 | N39: ✅ Verificado | O39: Alta | P39: Coincidencia exacta de nombre, dirección y teléfono en Google Places. 4.3★ (23 reseñas). | Q39: Google Places (place_id: ChIJdz_Up7Lbr5URiu1k63QG7eQ) - consultado 16/07/2026
A40: Inmobiliaria Ramirez Muñoz & Cia | B40: Inmobiliaria | C40: comercios | D40: Alberdi 511, Concepción del Uruguay, Entre Ríos, Argentina | E40: +54 9 3442 40-8157 | F40: -32.485559 | G40: -58.228649 | K40: Verificado (auditoría web múltiples fuentes) | L40: ChIJ-7-3RADbr5URqSGMUD4JlIM | M40: NUEVOSLUGARES5 | N40: ✅ Verificado | O40: Alta | P40: Confirmado por múltiples fuentes independientes (argentino.com.ar, bienesonline.com.ar, aspenbienesraices.com.ar, sitio propio ramirezmunioz.com.ar) coincidiendo en "Alberdi 511". | Q40: argentino.com.ar; aspenbienesraices.com.ar; ramirezmunioz.com.ar
A41: La Soñada. Barrio Privado. | B41: Barrio Privado | C41: comercios | D41: Prebistero Jorge Allais 2738, Concepción del Uruguay, Entre Ríos, Argentina | F41: -32.471548 | G41: -58.272503 | K41: Verificado (Google Places) | L41: ChIJo41igxjar5URJNbQ9MHm05g | M41: NUEVOSLUGARES5 | N41: ✅ Verificado | O41: Alta | P41: Coincidencia exacta de nombre, dirección y teléfono en Google Places. 4.3★ (264 reseñas). | Q41: Google Places (place_id: ChIJo41igxjar5URJNbQ9MHm05g) - consultado 16/07/2026
A42: INMOBILIARIA FERNAN GALOTTO | B42: Inmobiliaria | C42: comercios | D42: 9 de Julio Nº1655, E3260 Concepción del Uruguay, Entre Ríos, Argentina | E42: +54 3442 46-7285 | F42: -32.487778 | G42: -58.248931 | K42: Verificado (Google Places) | L42: ChIJc4MByarbr5UR2_mFviKfcIY | M42: NUEVOSLUGARES5 | N42: ✅ Verificado | O42: Alta | P42: Coincidencia exacta de nombre, dirección y teléfono en Google Places. 5.0★ (11 reseñas). | Q42: Google Places (place_id: ChIJc4MByarbr5UR2_mFviKfcIY) - consultado 16/07/2026
A43: DEFAZY PROPIEDADES | B43: Inmobiliaria | C43: comercios | D43: Ing. Henry 819, Concepción del Uruguay, Entre Ríos, Argentina | E43: +54 9 3442 54-6425 | F43: -32.489382 | G43: -58.233331 | K43: Verificado (auditoría web múltiples fuentes) | L43: ChIJm4RcEVHbr5URfZYZ5a0OaCM | M43: NUEVOSLUGARES5 | N43: ✅ Verificado | O43: Alta | P43: Confirmado por Cylex y por el sitio web oficial (defazyprop.com.ar), ambos coincidiendo en "Henry 819". | Q43: cylex.com.ar; defazyprop.com.ar
A44: Inmobiliaria Scatena | B44: Inmobiliaria | C44: comercios | D44: Juan Domingo Perón 257, Concepción del Uruguay, Entre Ríos, Argentina | E44: +54 3442 42-7764 | F44: -32.488142 | G44: -58.230695 | K44: Verificado (auditoría web múltiples fuentes) | L44: ChIJmV3cXQDbr5URu3puxay9Th4 | M44: NUEVOSLUGARES5 | N44: ✅ Verificado | O44: Alta | P44: Confirmado por múltiples directorios (argentino.com.ar, gloopla.com, linkbyme, inmuebleargentina.com) coincidiendo en "Juan D. Perón 257". | Q44: argentino.com.ar; gloopla.com; inmuebleargentina.com
A45: Charly Fabre PROPERTY MANAGEMENT | B45: Inmobiliaria | C45: comercios | D45: Sarmiento 359, E3260 Concepción del Uruguay, Entre Ríos, Argentina | E45: +54 9 3442 53-8519 | F45: -32.485752 | G45: -58.226039 | K45: Verificado (auditoría web múltiples fuentes) | L45: ChIJk8pr9ATbr5URB1MW--M-R4I | M45: NUEVOSLUGARES5 | N45: ✅ Verificado | O45: Alta | P45: Confirmado por Cylex (dos listados) y directorio concepciondeluruguay.com.ar, todos coincidiendo en "Sarmiento 359", con sitio propio fabreinmobiliaria.com.ar. | Q45: cylex.com.ar; concepciondeluruguay.com.ar; fabreinmobiliaria.com.ar
A46: Nexo Negocios Inmobiliarios | B46: Inmobiliaria | C46: comercios | D46: Bvd, Blvd. Dr. R. Uncal 879, E3260 Concepción del Uruguay, Entre Ríos, Argentina | E46: +54 9 3442 64-1700 | F46: -32.473199 | G46: -58.263954 | K46: Verificado (auditoría web múltiples fuentes) | L46: ChIJH1NU8qTbr5UR1bXvrVpAdlU | M46: NUEVOSLUGARES5 | N46: ✅ Verificado | O46: Alta | P46: Confirmado por Cylex y memudoya.com coincidiendo exactamente en "Blvd. Dr. R. Uncal 879". Otras fuentes más antiguas indican una dirección previa (Congreso de Tucumán 225), consistente con una mudanza de oficina. | Q46: cylex.com.ar; memudoya.com
A47: Margus Service Mechanic | B47: Taller Mecánico | C47: comercios | D47: Alfonsina Storni 1415, E3260 Concepción del Uruguay, Entre Ríos, Argentina | E47: +54 3442 50-8182 | F47: -32.465129 | G47: -58.253996 | K47: Verificado (auditoría web - fuente única) | L47: ChIJX8syRWrar5URMtQQejqupIE | M47: NUEVOSLUGARES5 | N47: ✅ Verificado | O47: Media | P47: Confirmado por directorio comercial (todosnegocios) con dirección exacta "Alfonsina Storni 1415" y teléfono coincidente. | Q47: ar.todosnegocios.com
A48: Svetko Mecánica | B48: Taller Mecánico | C48: comercios | D48: San Lorenzo 124, E3260 Concepción del Uruguay, Entre Ríos, Argentina | E48: +54 3442 49-7258 | F48: -32.487593 | G48: -58.238507 | K48: Verificado (auditoría web múltiples fuentes) | L48: ChIJO9-s2avbr5URrxgNbuY6eOw | M48: NUEVOSLUGARES5 | N48: ✅ Verificado | O48: Alta | P48: Confirmado por Facebook propio, tallermec.com.ar (con reseñas de clientes) y vymaps.com, todos coincidiendo en "San Lorenzo 124". | Q48: facebook.com/svetkomecanica; tallermec.com.ar; vymaps.com
A49: Taller mecánico Nico | B49: Taller Mecánico | C49: comercios | D49: Dr. J. Lacava 163, Concepción del Uruguay, Entre Ríos, Argentina | E49: +54 3442 68-3183 | F49: -32.486116 | G49: -58.253307 | H49: 4.7 | I49: 6 | K49: Verificado (Google Places API) | L49: ChIJKZjTBADbr5URlFoVfc76t7k | M49: Google Places API | N49: ✅ Verificado | O49: Alta | P49: Verificado vía Google Places API: existencia, dirección, coordenadas y place_id confirmados directamente. | Q49: Sin fuente que confirme existencia en la dirección indicada
A50: Taller Mecánico CHICHE | B50: Taller Mecánico | C50: comercios | D50: Concepción del Uruguay, Entre Ríos Province, Argentina | E50: +54 3442 40-0194 | F50: -32.485913 | G50: -58.284628 | H50: 5 | I50: 1 | K50: Verificado (Google Places API) | L50: ChIJ20O1VQDZr5URHWRq1l_2rFg | M50: Google Places API | N50: ✅ Verificado | O50: Alta | P50: Verificado vía Google Places API: existencia, dirección, coordenadas y place_id confirmados directamente. | Q50: Sin fuente que confirme existencia
A51: Yamil Servicio Mecánico | B51: Taller Mecánico | C51: comercios | D51: Isaias Torres 336, E3260 Concepción del Uruguay, Entre Ríos, Argentina | F51: -32.482232 | G51: -58.245926 | K51: Verificado (auditoría web múltiples fuentes) | L51: ChIJNfDolY3br5URhb36o2X0-Fw | M51: NUEVOSLUGARES5 | N51: ✅ Verificado | O51: Media | P51: Confirmado por página de Facebook propia y portal de reseñas (oopinoo, 18 opiniones) coincidiendo en nombre y rubro (taller mecánico). No se confirmó independientemente la dirección exacta (Isaías Torres 336). | Q51: ar.oopinoo.com; facebook.com/YAMIL.I.TOURNOUD
A52: Gimenez Servicio Mecánico | B52: Taller Mecánico | C52: comercios | D52: Calle publica 465 Nº2481 Publica 465, Salvarezza y, E3260 Concepción del Uruguay, Entre Ríos, Argentina | E52: +54 3442 62-3659 | F52: -32.481399 | G52: -58.267069 | H52: 5 | I52: 1 | K52: Verificado (Google Places - barrido de categoría) | L52: ChIJT5fbi1bbr5URP0x6u00cnK8 | M52: NUEVOSLUGARES5 | N52: ✅ Verificado | O52: Alta | P52: ACTUALIZACIÓN (comparación masiva vs. base maestra Google Places): se reemplaza la verificación previa por 'consistencia interna de datos' por confirmación externa real. Coincidencia exacta de Place ID, nombre, dirección y teléfono. | Q52: Google Places (place_id: ChIJT5fbi1bbr5URP0x6u00cnK8) - consultado 16/07/2026, vía barrido de base maestra por categoría
A53: Richard - Servicio Mecanico | B53: Taller Mecánico | C53: comercios | D53: Celia Torra 31, Concepción del Uruguay, Entre Ríos, Argentina | E53: +54 9 3442 48-3098 | F53: -32.487246 | G53: -58.249038 | K53: Verificado (auditoría web múltiples fuentes) | L53: ChIJmV3cXQDbr5UReU-HRwKQkEM | M53: NUEVOSLUGARES5 | N53: ✅ Verificado | O53: Alta | P53: Confirmado por múltiples fuentes independientes (Fresha, Waze, D&B, tallermec.com.ar, todosnegocios, Páginas Amarillas) y registro AFIP/CUIT (33716552379) con misma dirección (Celia Torra 31) y teléfono (03442 44-3766). Servicio oficial FIAT. | Q53: fresha.com; waze.com; dnb.com; tallermec.com.ar; todosnegocios.com; paginasamarillas.com.ar; w20argentina.com/AFIP-CUIT 33716552379
A54: Corocho mecanica | B54: Taller Mecánico | C54: comercios | D54: B° 134 Viviendas, Calle 390 Casa 1426, Concepción del Uruguay, Entre Ríos, Argentina | E54: +54 3442 60-3744 | F54: -32.462564 | G54: -58.249897 | H54: 5 | I54: 1 | K54: Verificado (Google Places - barrido de categoría) | L54: ChIJfeEeU-Lbr5URJ6WUkEP7yWc | M54: NUEVOSLUGARES5 | N54: ✅ Verificado | O54: Alta | P54: ACTUALIZACIÓN (comparación masiva vs. base maestra Google Places): se reemplaza la verificación previa por 'consistencia interna de datos' por confirmación externa real. Coincidencia exacta de Place ID, nombre, dirección y teléfono. | Q54: Google Places (place_id: ChIJfeEeU-Lbr5URJ6WUkEP7yWc) - consultado 16/07/2026, vía barrido de base maestra por categoría
A55: Mecanica El Enano® | B55: Taller Mecánico | C55: comercios | D55: J. J. Bruno 2762, Concepción del Uruguay, Entre Ríos, Argentina | E55: +54 3442 52-1872 | F55: -32.487438 | G55: -58.273285 | K55: Verificado (auditoría web múltiples fuentes) | L55: ChIJgTXaMk7ar5UR8fo4ekX7q3g | M55: NUEVOSLUGARES5 | N55: ✅ Verificado | O55: Alta | P55: Confirmado por sitio web oficial (mecanicaelenano.com.ar), Cybo, todosnegocios y reseñas en argentinafirm.com, todos coincidiendo en "J.J. Bruno 2762". | Q55: mecanicaelenano.com.ar; es.cybo.com; ar.todosnegocios.com
A56: LAZARTE SERVICIO MECANICO | B56: Taller Mecánico | C56: comercios | D56: Bv. Ricardo Balbín 1766, E3260 Concepción del Uruguay, Entre Ríos, Argentina | E56: +54 3442 44-1136 | F56: -32.47957 | G56: -58.253039 | K56: Verificado (auditoría web - fuente única) | L56: ChIJ-fi8Bv_br5URMO_ZKJdGC8w | M56: NUEVOSLUGARES5 | N56: ✅ Verificado | O56: Media | P56: Confirmado por tallermec.com.ar (con reseñas de clientes) con dirección exacta "Bv. Ricardo Balbín 1766", coincide con el dataset. | Q56: tallermec.com.ar
A57: GRUPO LEÓN S.A. | B57: Mayorista | C57: comercios | D57: RUTA PROVINCIAL Nº 39 KM 146, 3260 Concepción del Uruguay, Entre Ríos, Argentina | E57: +54 800-444-0479 | F57: -32.48501 | G57: -58.313801 | K57: Verificado (fuente oficial - AFIP/CUIT y sitio propio) | L57: ChIJhcJZQynar5URPzsr4HMxsvI | M57: NUEVOSLUGARES5 | N57: ✅ Verificado | O57: Alta | P57: Confirmado por registro oficial de AFIP/CUIT (CUIT 30-71697594-7, persona jurídica, domicilio fiscal "Ruta N°39 Km 146", Concepción del Uruguay, alta 2020-08-20) y por el sitio web corporativo propio (grupoleonsa.com), que describe a "León Mayorista" como su unidad de negocio pionera con sede en la ciudad. Coincide razón social, rubro (venta al por mayor) y localidad. | Q57: cuitonline.com (CUIT 30716975947); grupoleonsa.com
A58: Mayorista del Puerto | B58: Mayorista | C58: comercios | D58: Av. Costanera Paysandú, Concepción del Uruguay, Entre Ríos, Argentina | E58: +54 3442 42-2210 | F58: -32.480274 | G58: -58.22229 | K58: Verificado (auditoría web múltiples fuentes) | L58: ChIJ45SBGxvbr5URwtvY6RZ7Xj0 | M58: NUEVOSLUGARES5 | N58: ✅ Verificado | O58: Alta | P58: Confirmado por múltiples fuentes independientes: página de Instagram propia (@mayoristadelpuerto, +10.000 seguidores), página de Facebook (delpuertomayorista) y directorios/reseñas (directoriomayorista.com, argentopina.com, Waze), todas coincidiendo en dirección (Av. Costanera Paysandú, esquina 8 de Junio) y teléfono (+54 3442 42-2210), idéntico al de la planilla. | Q58: instagram.com/mayoristadelpuerto; facebook.com/delpuertomayorista; directoriomayorista.com; argentopina.com; waze.com
A59: Distribuidora BDB | B59: Distribuidora | C59: comercios | D59: Goytia 1585, E3260 Concepción del Uruguay, Entre Ríos, Argentina | E59: +54 9 3442 31-1178 | F59: -32.471167 | G59: -58.251939 | K59: Verificado (Google Places - barrido de categoría) | L59: ChIJk5lPb7Pbr5URxwrWkaNjBsU | M59: NUEVOSLUGARES5 | N59: ✅ Verificado | O59: Alta | P59: ACTUALIZACIÓN (comparación masiva vs. base maestra Google Places): se reemplaza la verificación previa por 'consistencia interna de datos' por confirmación externa real. Coincidencia exacta de Place ID, nombre, dirección y teléfono. Sin reseñas en Google. | Q59: Google Places (place_id: ChIJk5lPb7Pbr5URxwrWkaNjBsU) - consultado 16/07/2026, vía barrido de base maestra por categoría
A60: Premium distribuidora | B60: Distribuidora | C60: comercios | D60: 9 de Julio 1236, Concepción del Uruguay, Entre Ríos, Argentina | E60: +54 3442 43-9988 | F60: -32.486332 | G60: -58.241134 | K60: Verificado (auditoría web múltiples fuentes) | L60: ChIJBSmsfKzbr5URUyXmHEQTHgQ | M60: NUEVOSLUGARES5 | N60: ✅ Verificado | O60: Alta | P60: Confirmado por múltiples fuentes independientes (Facebook, Superanuncios, GuiaDeArgentina, RedArgentina, LaGuia.online, LatinoPlaces) con misma dirección (9 de Julio 1236) y teléfono (03442 43-9988). | Q60: facebook.com/PREMIUMDISTRIBUIDORASHOP; superanuncios.com.ar; guiadeargentina.com.ar; redargentina.com.ar; laguia.online; ar.latinoplaces.com
A61: Center Mayorista | B61: Mayorista | C61: comercios | D61: Bv. Ricardo Balbín, E3260 Concepción del Uruguay, Entre Ríos, Argentina | F61: -32.476746 | G61: -58.285891 | K61: Verificado (auditoría web múltiples fuentes) | L61: ChIJI95RRwDZr5URHhi_j3oXYgU | M61: NUEVOSLUGARES5 | N61: ✅ Verificado | O61: Media | P61: Confirmado por sitio propio (centermayoristas.com) e Instagram oficial (@mayoristascenter), ambos ubicando el negocio en Bv. Ricardo Balbín, Concepción del Uruguay (numeración 4050 según Instagram; el archivo no tenía numeración). | Q61: centermayoristas.com; instagram.com/mayoristascenter
A62: Yaguareté | B62: Mayorista | C62: comercios | D62: Sansoni 1850, E3260 Concepción del Uruguay, Entre Ríos, Argentina | F62: -32.486798 | G62: -58.252699 | K62: Verificado (auditoría web múltiples fuentes) | L62: ChIJ5dYOsrTbr5UR-TQ0LqDnGXY | M62: NUEVOSLUGARES5 | N62: ✅ Verificado | O62: Alta | P62: Confirmado por múltiples fuentes independientes (Facebook, Instagram, portal de noticias local 03442.com.ar, findglocal) con misma dirección exacta (Sansoni 1850). | Q62: facebook.com/mayoristayaguarete; instagram.com/mayoristayaguarete; 03442.com.ar; findglocal.com
A63: El 12- Mayorista y minorista | B63: Mayorista | C63: comercios | D63: Justo José de Urquiza 733, Concepción del Uruguay, Entre Ríos, Argentina | F63: -32.473934 | G63: -58.23528 | K63: Verificado (auditoría web múltiples fuentes) | L63: ChIJdbuImt3br5URuKrERcm-DA8 | M63: NUEVOSLUGARES5 | N63: ✅ Verificado | O63: Alta | P63: Confirmado por Facebook oficial con dirección exacta (Urquiza 733). | Q63: facebook.com/mayoristaminoristael12
A64: Mayorista y Minorista El Rey León | B64: Mayorista | C64: comercios | D64: 8 de Junio 2850, E3260 Concepción del Uruguay, Entre Ríos, Argentina | E64: +54 3442 68-1704 | F64: -32.487406 | G64: -58.275964 | H64: 4.3 | I64: 12 | K64: Verificado (Google Places - barrido de categoría) | L64: ChIJT3VQCgDbr5URJRjPHnugM9k | M64: NUEVOSLUGARES5 | N64: ✅ Verificado | O64: Alta | P64: ACTUALIZACIÓN (comparación masiva vs. base maestra Google Places): se reemplaza la verificación previa por 'consistencia interna de datos' por confirmación externa real. Coincidencia exacta de Place ID, nombre, dirección y teléfono. | Q64: Google Places (place_id: ChIJT3VQCgDbr5URJRjPHnugM9k) - consultado 16/07/2026, vía barrido de base maestra por categoría
A65: Electro Aguirre SRL | B65: Electricidad | C65: comercios | D65: 9 de Julio 1342, Concepción del Uruguay, Entre Ríos, Argentina | E65: +54 3442 30-7509 | F65: -32.48648 | G65: -58.243247 | K65: Verificado (auditoría web múltiples fuentes) | L65: ChIJoZINXQDbr5UR9C5VnwOg6WY | M65: NUEVOSLUGARES5 | N65: ✅ Verificado | O65: Alta | P65: Confirmado por Waze, Facebook, sitio propio (electro-aguirre.com.ar), argentino.com.ar y laguia.online con misma dirección (9 de Julio 1342). | Q65: waze.com; facebook.com; electro-aguirre.com.ar; argentino.com.ar; laguia.online
A66: SUELECTRIC Materiales Electricos | B66: Electricidad | C66: comercios | D66: Gral. Galarza 1239, E3260 Concepción del Uruguay, Entre Ríos, Argentina | E66: +54 3442 42-6333 | F66: -32.485548 | G66: -58.241446 | K66: Verificado (auditoría web múltiples fuentes) | L66: ChIJmV3cXQDbr5URI3EwKoPycL4 | M66: NUEVOSLUGARES5 | N66: ✅ Verificado | O66: Alta | P66: Confirmado por sitio propio (suelectric.net), Facebook, Wikimapia y reseñas de Google con misma dirección exacta (Galarza 1239). | Q66: suelectric.net; facebook.com/suelectric; wikimapia.org; milruedas.es
A67: Electricidad Del Automotor | B67: Electricidad automotor | C67: comercios | D67: Blvd. Dr. R. Uncal 341, Concepción del Uruguay, Entre Ríos, Argentina | F67: -32.478102 | G67: -58.240254 | K67: Verificado (auditoría web múltiples fuentes) | L67: ChIJGUa7RzTar5URnOCU7iN1oSo | M67: NUEVOSLUGARES5 | N67: ✅ Verificado | O67: Media | P67: Confirmado por múltiples directorios independientes (argentino.com.ar, redargentina, Páginas Amarillas, laguiadeargentina, licuo) con misma dirección exacta (Bv. R. Uncal 341). | Q67: argentino.com.ar; redargentina.com.ar; paginasamarillas.com.ar; laguiadeargentina.com; licuo.com.ar
A68: La casa del Encendido | B68: Repuestos automotor | C68: comercios | D68: Gral. Galarza 1174, E3260 Concepción del Uruguay, Entre Ríos, Argentina | F68: -32.485202 | G68: -58.240175 | K68: Verificado (auditoría web múltiples fuentes) | L68: ChIJv817fKvbr5UR12gvTA_r7aQ | M68: NUEVOSLUGARES5 | N68: ✅ Verificado | O68: Alta | P68: Confirmado por Instagram oficial, argentino.com.ar, dirtel.com.ar e infoisinfo con misma dirección (Galarza 1174/1178, ligera variación de numeración entre fuentes). | Q68: instagram.com/lacasadelencendido; argentino.com.ar; dirtel.com.ar; infoisinfo-ar.com
A69: Electromecanica Galarza | B69: Electromecánica automotor | C69: comercios | D69: República del Líbano 27, Concepción del Uruguay, Entre Ríos, Argentina | E69: +54 3442 42-5040 | F69: -32.487098 | G69: -58.248115 | K69: Verificado (auditoría web múltiples fuentes) | L69: ChIJi-0e8rLbr5UROaAmkrYF8QU | M69: NUEVOSLUGARES5 | N69: ✅ Verificado | O69: Alta | P69: Confirmado por Facebook, Cylex, horarios.me y otras guías con misma dirección exacta (República del Líbano 27). | Q69: facebook.com/ElectromecanicaGalarza; cylex.com.ar; horarios.me
A70: LOPELEC - Materiales Electricos | B70: Electricidad | C70: comercios | D70: 9 de Julio 1650, E3260 Concepción del Uruguay, Entre Ríos, Argentina | E70: +54 3442 67-9348 | F70: -32.48755 | G70: -58.248728 | K70: Verificado (auditoría web múltiples fuentes) | L70: ChIJoZINXQDbr5UR94BR-Ag94Ps | M70: NUEVOSLUGARES5 | N70: ✅ Verificado | O70: Alta | P70: Confirmado por múltiples directorios (cumaps.net, vymaps.com, ar.oopinoo.com) con misma dirección exacta (9 de Julio 1650) y coordenadas. | Q70: cumaps.net; vymaps.com; ar.oopinoo.com
A71: Electro Integral Sh de Bertti Miriam y Caire Delio | B71: Electricidad | C71: comercios | D71: San Martín 900, E3260 Concepción del Uruguay, Entre Ríos, Argentina | E71: +54 3442 42-4669 | F71: -32.485916 | G71: -58.235283 | K71: Verificado (auditoría web múltiples fuentes) | L71: ChIJVxGIDqrbr5URhh0UkPhNzyg | M71: NUEVOSLUGARES5 | N71: ✅ Verificado | O71: Alta | P71: Confirmado por Cylex, sase.com.ar e infoisinfo con misma dirección exacta (San Martín 900). | Q71: cylex.com.ar; sase.com.ar; infoisinfo-ar.com; mapcarta.com
A72: Magri Repuestos | B72: Repuestos automotor | C72: comercios | D72: Posadas 1349, E3260ATM Concepción del Uruguay, Entre Ríos, Argentina | E72: +54 3442 42-5974 | F72: -32.483883 | G72: -58.243818 | K72: Verificado (auditoría web múltiples fuentes) | L72: ChIJ5XEhnU_br5URACxaJ_Lho60 | M72: NUEVOSLUGARES5 | N72: ✅ Verificado | O72: Alta | P72: Confirmado por Facebook oficial, guiaurbana.com.ar, Páginas Amarillas y mobidoc.com.ar con misma dirección (Posadas 1349). | Q72: facebook.com/MagriRepuestos; guiaurbana.com.ar; paginasamarillas.com.ar; mobidoc.com.ar
A73: Electro Aguirre Iluminación | B73: Iluminación | C73: comercios | D73: España 90, Concepción del Uruguay, Entre Ríos, Argentina | E73: +54 3442 43-3881 | F73: -32.486215 | G73: -58.233462 | H73: 4.5 | I73: 31 | K73: Verificado (Google Places - barrido de categoría) | L73: ChIJYZjItQDbr5URR-VD-WhV0oQ | M73: NUEVOSLUGARES5 | N73: ✅ Verificado | O73: Alta | P73: ACTUALIZACIÓN (comparación masiva vs. base maestra Google Places): se reemplaza la verificación previa por 'consistencia interna de datos' por confirmación externa real. Coincidencia exacta de Place ID, nombre y dirección. | Q73: Google Places (place_id: ChIJYZjItQDbr5URR-VD-WhV0oQ) - consultado 16/07/2026, vía barrido de base maestra por categoría
A74: Uruguay Repuestos | B74: Repuestos automotor | C74: comercios | D74: 9 de julio, Dr. Dodero y, Concepción del Uruguay, Entre Ríos, Argentina | E74: +54 3442 64-9522 | F74: -32.486941 | G74: -58.24418 | K74: Verificado (auditoría web múltiples fuentes) | L74: ChIJbVXSCa3br5UR5DOSntJ3iDI | M74: NUEVOSLUGARES5 | N74: ✅ Verificado | O74: Alta | P74: Confirmado por Facebook e Instagram oficiales con misma dirección (esquina 9 de Julio y Dr. Dodero). | Q74: facebook.com/uruguay.repuestos; instagram.com/uruguay.repuestos
A75: Abogado Nahuel Nuñez | B75: Abogado | C75: comercios | D75: Mariano Moreno 122, E3260 Concepción del Uruguay, Entre Ríos, Argentina | E75: +54 3442 40-6677 | F75: -32.486354 | G75: -58.231733 | K75: Verificado con diferencias (auditoría web - prensa local) | L75: ChIJFxha_HHbr5URgAm3VowBDL4 | M75: NUEVOSLUGARES5 | N75: 🟡 Verificado con diferencias | O75: Media | P75: INCONSISTENCIA DETECTADA: la existencia del abogado Nahuel Núñez y su estudio jurídico en Concepción del Uruguay está confirmada por una nota periodística (Vía Gualeguaychú, 2020) sobre un incidente ocurrido frente al estudio. Sin embargo, la nota ubica el estudio en la intersección de calles Malvar y Pinto esquina Rivadavia, no en "Mariano Moreno 122" como figura en la planilla. No se halló fuente que confirme la dirección de la planilla; podría tratarse de una mudanza posterior o de un domicilio adicional. Requiere confirmación manual de la dirección actual. | Q75: viapais.com.ar/gualeguaychu (nota del 15/11/2020) - no confirma dirección de la planilla
A76: ESTUDIO JURÍDICO •PIERINA MERCURIO ABOGADA• | B76: Abogado | C76: comercios | D76: 3 de Febrero Nº 80, E3260 Concepción del Uruguay, Entre Ríos, Argentina | E76: +54 3442 64-2518 | F76: -32.485842 | G76: -58.232701 | K76: Verificado (auditoría web múltiples fuentes) | L76: ChIJn7eoP27br5URtGTkxrlDFvE | M76: NUEVOSLUGARES5 | N76: ✅ Verificado | O76: Alta | P76: Confirmado por directorio del Colegio de la Abogacía de Entre Ríos con misma dirección exacta (3 de Febrero N° 80). | Q76: todosnegocios.com (Caja Forense de Entre Ríos)
A77: Estudio Jurídico Rousseaux - Abogados | B77: Abogado | C77: comercios | D77: Artusi 874, E3260 Concepción del Uruguay, Entre Ríos, Argentina | E77: +54 9 3442 47-8750 | F77: -32.480736 | G77: -58.23595 | K77: Verificado (auditoría web múltiples fuentes) | L77: ChIJVbLXQ1Xar5URCSoGBSRLH30 | M77: NUEVOSLUGARES5 | N77: ✅ Verificado | O77: Alta | P77: Confirmado por sitio propio, Facebook, Cylex y listado del Colegio de Abogados de Entre Ríos con misma dirección exacta (Artusi 874). | Q77: estudio-juridico-rousseaux-abogados.negocio.site; facebook.com/erabogadosok; cylex.com.ar; findglocal.com
A78: Abogada Tatiana Bozzolo - Estudio Juridico y Centro de Mediacion | B78: Abogado | C78: comercios | D78: Gral. Galarza 734 1er piso 7, E3260 Concepción del Uruguay, Entre Ríos, Argentina | E78: +54 3442 41-8629 | F78: -32.483948 | G78: -58.232845 | H78: 5 | I78: 1 | K78: Verificado (Google Places - barrido de categoría) | L78: ChIJ060h46zbr5URkVy1usVJI6E | M78: NUEVOSLUGARES5 | N78: ✅ Verificado | O78: Alta | P78: ACTUALIZACIÓN (comparación masiva vs. base maestra Google Places): se reemplaza la verificación previa por 'consistencia interna de datos' por confirmación externa real. Coincidencia exacta de Place ID, nombre, dirección y teléfono. | Q78: Google Places (place_id: ChIJ060h46zbr5URkVy1usVJI6E) - consultado 16/07/2026, vía barrido de base maestra por categoría
A79: Maria Carolina Carbó- Estudio Jurídico | B79: Abogado | C79: comercios | D79: Zubiaur 129 2do piso oficina 1, E3260 Concepción del Uruguay, Entre Ríos, Argentina | E79: +54 343 472-3434 | F79: -32.480869 | G79: -58.222444 | H79: 5 | I79: 34 | K79: Verificado (Google Places - barrido de categoría) | L79: ChIJR4NjAPTbr5UR1X63PjftWEE | M79: NUEVOSLUGARES5 | N79: ✅ Verificado | O79: Alta | P79: ACTUALIZACIÓN (comparación masiva vs. base maestra Google Places): se reemplaza la verificación previa por 'consistencia interna de datos' por confirmación externa real. Coincidencia exacta de Place ID, nombre, dirección y teléfono. | Q79: Google Places (place_id: ChIJR4NjAPTbr5UR1X63PjftWEE) - consultado 16/07/2026, vía barrido de base maestra por categoría
A80: Haddad & Asociados | B80: Estudio Jurídico | C80: comercios | D80: Almafuerte 890, E3260 Concepción del Uruguay, Entre Ríos, Argentina | E80: +54 3442 42-5123 | F80: -32.487932 | G80: -58.234813 | K80: Verificado (auditoría web múltiples fuentes) | L80: ChIJ-yUlYAfbr5URa1wYiIt_Z2Y | M80: NUEVOSLUGARES5 | N80: ✅ Verificado | O80: Alta | P80: Confirmado por sitio propio (haddadyasoc.com.ar) y Cylex con misma dirección exacta (Almafuerte 890). | Q80: haddadyasoc.com.ar; cylex.com.ar
A81: Estudio jurídico Vela & Asociados | B81: Abogado | C81: comercios | D81: Blvd. Hipólito Yrigoyen 767, E3260 Concepción del Uruguay, Entre Ríos, Argentina | E81: +54 3442 33-8497 | F81: -32.477729 | G81: -58.234554 | H81: 5 | I81: 1 | K81: Verificado (Google Places - barrido de categoría) | L81: ChIJtbMkN3zbr5URx_9EptvC_OQ | M81: NUEVOSLUGARES5 | N81: ✅ Verificado | O81: Alta | P81: ACTUALIZACIÓN (comparación masiva vs. base maestra Google Places): se reemplaza la verificación previa por 'consistencia interna de datos' por confirmación externa real. Coincidencia exacta de Place ID, nombre, dirección y teléfono. | Q81: Google Places (place_id: ChIJtbMkN3zbr5URx_9EptvC_OQ) - consultado 16/07/2026, vía barrido de base maestra por categoría
A82: Estudio Juridico - Saucedo Laura | B82: Abogado | C82: comercios | D82: Juan Domingo Perón 89, E3264 Concepción del Uruguay, Entre Ríos, Argentina | E82: +54 3442 43-3502 | F82: -32.485758 | G82: -58.231262 | K82: Verificado (auditoría web múltiples fuentes) | L82: ChIJmV3cXQDbr5URuwPxK7HEcjM | M82: NUEVOSLUGARES5 | N82: ✅ Verificado | O82: Alta | P82: Confirmado por el Boletín Oficial de Entre Ríos (fuente oficial), que registra a la Abogada Laura Angélica Saucedo con domicilio constituido en Juan Domingo Perón Nº 87, coincidente con la dirección del archivo (Nº89). | Q82: entrerios.gov.ar (Boletín Oficial)
A83: Estudio jurídico Ostolaza | B83: Abogado | C83: comercios | D83: M. Álvarez 219, Concepción del Uruguay, Entre Ríos, Argentina | E83: +54 3442 48-1199 | F83: -32.479788 | G83: -58.223691 | H83: 5 | I83: 4 | K83: Verificado (Google Places - barrido de categoría) | L83: ChIJqfo7dKTbr5URY0AqL-eCohw | M83: NUEVOSLUGARES5 | N83: ✅ Verificado | O83: Alta | P83: ACTUALIZACIÓN (comparación masiva vs. base maestra Google Places): se reemplaza la verificación previa por 'consistencia interna de datos' por confirmación externa real. Coincidencia exacta de Place ID, nombre, dirección y teléfono. | Q83: Google Places (place_id: ChIJqfo7dKTbr5URY0AqL-eCohw) - consultado 16/07/2026, vía barrido de base maestra por categoría
A84: Estudio Juridico Bernal | B84: Abogado | C84: comercios | D84: Tibiletti 11, Concepción del Uruguay, Entre Ríos, Argentina | E84: +54 3442 42-3716 | F84: -32.484432 | G84: -58.229771 | H84: 4.6 | I84: 34 | K84: Verificado (Google Places - barrido de categoría) | L84: ChIJ-7-3RADbr5URZmoTSttQZls | M84: NUEVOSLUGARES5 | N84: ✅ Verificado | O84: Alta | P84: ACTUALIZACIÓN (comparación masiva vs. base maestra Google Places): se reemplaza la verificación previa por 'consistencia interna de datos' por confirmación externa real. Coincidencia exacta de Place ID, nombre, dirección y teléfono. | Q84: Google Places (place_id: ChIJ-7-3RADbr5URZmoTSttQZls) - consultado 16/07/2026, vía barrido de base maestra por categoría
A85: Escribania Vaccalluzzo | B85: Escribanía | C85: comercios | D85: San Martín 832, Concepción del Uruguay, Entre Ríos, Argentina | E85: +54 3442 42-5758 | F85: -32.485705 | G85: -58.234206 | K85: Verificado (auditoría web múltiples fuentes) | L85: ChIJoZINXQDbr5UR-m2fHp58VyE | M85: NUEVOSLUGARES5 | N85: ✅ Verificado | O85: Alta | P85: Confirmado por sitio propio (escribaniavaccalluzzo.com) y múltiples directorios con misma dirección exacta (San Martín 832). | Q85: escribaniavaccalluzzo.com; guiaurbana.com.ar; escribanos.aarg.ar; arempresas.com
A86: Escribania Vivas | B86: Escribanía | C86: comercios | D86: 8 de Junio 609, Concepción del Uruguay, Entre Ríos, Argentina | E86: +54 3442 42-4989 | F86: -32.482253 | G86: -58.231022 | K86: Verificado (auditoría web múltiples fuentes) | L86: ChIJ-7-3RADbr5UR5nNHMAprgbw | M86: NUEVOSLUGARES5 | N86: ✅ Verificado | O86: Alta | P86: Confirmado por múltiples directorios independientes con misma dirección exacta (8 de Junio 609). | Q86: infobel.com; guiaurbana.com.ar; escribanos.aarg.ar; misterwhat.com.ar
A87: Escribania Vallarino | B87: Escribanía | C87: comercios | D87: 25 de Mayo 168, Concepción del Uruguay, Entre Ríos, Argentina | E87: +54 3442 42-5766 | F87: -32.482231 | G87: -58.232446 | K87: Verificado (auditoría web múltiples fuentes) | L87: ChIJ-7-3RADbr5URt_6gLzbScSI | M87: NUEVOSLUGARES5 | N87: ✅ Verificado | O87: Media | P87: Confirmado por directorio especializado de escribanos (aarg.ar) y directorio cruzado (misterwhat.com.ar) con misma dirección exacta (25 de Mayo 168). | Q87: escribanos.aarg.ar; misterwhat.com.ar
A88: Escribania Lacava | B88: Escribanía | C88: comercios | D88: Ereño 862, Concepción del Uruguay, Entre Ríos, Argentina | E88: +54 3442 42-2249 | F88: -32.488548 | G88: -58.234108 | K88: Verificado (auditoría web múltiples fuentes) | L88: ChIJ-7-3RADbr5URE2UH6X-21D0 | M88: NUEVOSLUGARES5 | N88: ✅ Verificado | O88: Media | P88: Confirmado por directorio especializado de escribanos (aarg.ar) y directorio cruzado (megargbiz.com) con misma dirección exacta (Ereño 862). | Q88: escribanos.aarg.ar; megargbiz.com
A89: Poetto, Ariel Adhemar | B89: Escribanía | C89: comercios | D89: Rocamora 1360, Concepción del Uruguay, Entre Ríos, Argentina | E89: +54 3442 43-0814 | F89: -32.485158 | G89: -58.243833 | K89: Verificado (auditoría web múltiples fuentes) | L89: ChIJ-7-3RADbr5UR4UBHmuhk8uc | M89: NUEVOSLUGARES5 | N89: ✅ Verificado | O89: Alta | P89: Confirmado por registro CUIT/AFIP (rocamora 1360) y múltiples directorios (Rocamora 1352/1360, variación menor de numeración) con mismo nombre y localidad. | Q89: cuitonline.com; redargentina.com.ar; az-argentina.com; miguiaargentina.com.ar
A90: Dominutti de Bisogni Olga | B90: Escribanía | C90: comercios | D90: Gral. Galarza 952, Concepción del Uruguay, Entre Ríos, Argentina | E90: +54 3442 42-2691 | F90: -32.484603 | G90: -58.236603 | K90: Verificado (auditoría web múltiples fuentes) | L90: ChIJ-7-3RADbr5URrBZm_be-spY | M90: NUEVOSLUGARES5 | N90: ✅ Verificado | O90: Alta | P90: Confirmado por redargentina.com.ar y tuescribania.com con misma dirección exacta (Galarza 952). | Q90: redargentina.com.ar; tuescribania.com
A91: Escribania Negri | B91: Escribanía | C91: comercios | D91: Leandro N. Alem 68, Concepción del Uruguay, Entre Ríos, Argentina | E91: +54 3442 42-4567 | F91: -32.486061 | G91: -58.23438 | K91: Verificado (auditoría web múltiples fuentes) | L91: ChIJ-7-3RADbr5URDKAyHykJNj8 | M91: NUEVOSLUGARES5 | N91: ✅ Verificado | O91: Alta | P91: Confirmado por Páginas Amarillas y múltiples directorios con misma dirección exacta (Leandro N. Alem 68). | Q91: paginasamarillas.com.ar; argentino.com.ar; tuescribania.com; escribaniasargentina.com
A92: Colegio de Escribanos de Entre Rios | B92: Colegio profesional | C92: comercios | D92: O Leguizamón 189, Concepción del Uruguay, Entre Ríos, Argentina | E92: +54 3442 42-3863 | F92: -32.483 | G92: -58.233 | K92: Verificado (auditoría web múltiples fuentes) | L92: ChIJ-7-3RADbr5URWz1UF1hMF2A | M92: NUEVOSLUGARES5 | N92: ✅ Verificado | O92: Alta | P92: Confirmado por Páginas Amarillas y múltiples directorios independientes con misma dirección exacta (O Leguizamón 189). | Q92: paginasamarillas.com.ar; todosnegocios.com; az-argentina.com; formacionargentina.com
A93: Nichele Verónica | B93: Escribanía | C93: comercios | D93: 3 de Febrero 80, E3260 Concepción del Uruguay, Entre Ríos, Argentina | E93: +54 3442 42-7964 | F93: -32.485842 | G93: -58.232701 | K93: Verificado (auditoría web múltiples fuentes) | L93: ChIJ-7-3RADbr5UR1ydnLpJbR9Y | M93: NUEVOSLUGARES5 | N93: ✅ Verificado | O93: Alta | P93: Confirmado por fuente oficial (listado de notarios adheridos, anses.gob.ar) y registro CUIT/AFIP con misma dirección exacta (3 de Febrero 80). | Q93: anses.gob.ar; cuitonline.com; abctelefonos.com
A94: Gluschancoff Mario Jose | B94: Escribanía/Finanzas | C94: comercios | D94: Gral. Galarza 637, Concepción del Uruguay, Entre Ríos, Argentina | E94: +54 3442 42-2535 | F94: -32.483 | G94: -58.233 | K94: Verificado (auditoría web múltiples fuentes) | L94: ChIJ-7-3RADbr5URO1qtKWWkals | M94: NUEVOSLUGARES5 | N94: ✅ Verificado | O94: Alta | P94: Confirmado por redargentina.com.ar y misterwhat.com.ar con misma dirección exacta (Galarza 637). | Q94: redargentina.com.ar; misterwhat.com.ar
A95: Palacio San José (Museo Nacional Justo José de Urquiza) | B95: Patrimonio histórico | C95: patrimonio | D95: Ruta Provincial 39, Km 128, Caseros, Depto. Uruguay, Entre Ríos | F95: -32.42775 | G95: -58.52039 | H95: 4.6 | I95: 12068 | J95: Museo y Monumento Histórico Nacional. Residencia de Urquiza. | K95: Verificado (fuente oficial - Ministerio de Cultura) | L95: ChIJ4QInqMUtsJURlCiiklmd1DI | M95: lugaresmaapapspapr | N95: ✅ Verificado | O95: Alta | P95: Confirmado por el sitio oficial del museo (museourquiza.cultura.gob.ar) y el portal Modalia del Ministerio de Cultura de la Nación. Dirección coincidente: Ruta Provincial N°39 Km 128, zona rural, Caseros, Depto. Uruguay. | Q95: museourquiza.cultura.gob.ar; modalia.cultura.gob.ar; entreriosturismo.com.ar
A96: Basílica Menor Inmaculada Concepción | B96: Patrimonio histórico | C96: patrimonio | D96: 3 de Febrero 41, Concepción del Uruguay, Entre Ríos | E96: +54 3442 42-7146 | F96: -32.48515 | G96: -58.23306 | H96: 4.7 | I96: 1155 | J96: Alberga el mausoleo de Urquiza. | K96: Verificado (fuente oficial - Monumento Histórico Nacional) | L96: ChIJB1MGvwDbr5UR5-KDt-6jfXo | M96: lugaresmaapapspapr | N96: ✅ Verificado | O96: Alta | P96: Confirmado por argentina.gob.ar (listado oficial de monumentos históricos, Decreto 112.765/1942) y por Dirección de Turismo municipal (3260.com.ar). Dirección y teléfono coinciden exactamente con la planilla (3 de Febrero 41, +54 3442 42-7146). | Q96: argentina.gob.ar/capital-humano/cultura/monumentos; 3260.com.ar; horariomisas.com.ar
A97: Museo Casa Delio Panizza (MHN) | B97: Patrimonio histórico | C97: patrimonio | D97: Supremo Entrerriano 58, Concepción del Uruguay, Entre Ríos | F97: -32.48349 | G97: -58.23055 | H97: 4.6 | I97: 179 | K97: Verificado (auditoría web múltiples fuentes) | L97: ChIJCwN5DgHbr5URr9IEnzO--60 | M97: lugaresmaapapspapr | N97: ✅ Verificado | O97: Alta | P97: Confirmado por Turismo Entre Ríos (turismo-cultura-historia) y por página oficial de Facebook del museo, además de artículo de prensa local. Declarado Monumento Histórico Nacional en 1975. Ubicación coincidente: a una cuadra de la plaza principal (Supremo Entrerriano 58). | Q97: entrerios.tur.ar; facebook.com/Museo-Casa-Delio-Panizza; laciudadrevista.com; analisisdigital.com.ar
A98: Museo Andrés García (MHN) | B98: Patrimonio histórico | C98: patrimonio | D98: Supremo Entrerriano 31, Concepción del Uruguay, Entre Ríos | F98: -32.48394 | G98: -58.23079 | H98: 4.2 | I98: 41 | K98: Verificado (fuente oficial - Turismo Entre Ríos) | L98: ChIJ4Xl9AwHbr5URwiLuMwoXHjg | M98: lugaresmaapapspapr | N98: ✅ Verificado | O98: Alta | P98: Confirmado por Turismo Entre Ríos: ubicación "Galarza y Supremo Entrerriano", consistente con la dirección de la planilla (Supremo Entrerriano 31). Repositorio histórico del acervo entrerriano, colección del Sr. Andrés García. | Q98: entrerios.tur.ar/turismo-cultura-historia/museos-en-concepcion-del-uruguay-y-alrededores
A99: Colegio Superior del Uruguay 'Justo José de Urquiza' | B99: Patrimonio histórico | C99: patrimonio | D99: Leguizamón 24, Concepción del Uruguay, Entre Ríos | E99: +54 3442 42-5554 | F99: -32.48446 | G99: -58.23378 | K99: Verificado (auditoría web múltiples fuentes) | L99: ChIJqwEEkgDbr5URC5XUtP8hQqQ | M99: lugaresmaapapspapr | N99: ✅ Verificado | O99: Alta | P99: Confirmado por múltiples directorios educativos independientes, todos coincidentes en la dirección exacta "Leguizamón 24". Institución declarada Monumento Histórico Nacional en 1942, fundada en 1849 por Urquiza. | Q99: ifts1.com.ar; ofertaeducativasr.com.ar; schoolandcollegelistings.com
A100: Santa Cándida (hostería) | B100: Patrimonio histórico | C100: patrimonio | D100: Puente Fierro s/n, Concepción del Uruguay, Entre Ríos | E100: +54 11 2049-9747 | F100: -32.51175 | G100: -58.23639 | H100: 4.6 | I100: 203 | K100: Verificado (auditoría web múltiples fuentes) | L100: ChIJvTvnPp3br5URBsP7nF2CFK0 | M100: lugaresmaapapspapr | N100: ✅ Verificado | O100: Alta | P100: Confirmado por múltiples plataformas de hotelería (Tripadvisor, Expedia, Hotels.com) coincidentes en dirección exacta "Puente de Fierro", Concepción del Uruguay. Castillo/hostería de 3 estrellas con reseñas activas. | Q100: tripadvisor.com; expedia.com; hotels.com
...

Sheet Resumen
A1: Resumen de Lugares
A3: Total de lugares: | B3: =COUNTA(Todos!A2:A1586) -> 1585
A5: Grupo | B5: Cantidad | D5: Categoría | E5: Cantidad
A6: alojamiento | B6: =COUNTIF(Todos!C2:C1586,A6) -> 32 | D6: Aberturas | E6: =COUNTIF(Todos!B2:B1586,D6) -> 5
A7: belleza | B7: =COUNTIF(Todos!C2:C1586,A7) -> 99 | D7: Aberturas / Carpintería de aluminio | E7: =COUNTIF(Todos!B2:B1586,D7) -> 1
A8: comercios | B8: =COUNTIF(Todos!C2:C1586,A8) -> 93 | D8: Abogado | E8: =COUNTIF(Todos!B2:B1586,D8) -> 20
A9: compras | B9: =COUNTIF(Todos!C2:C1586,A9) -> 265 | D9: Academia de idiomas | E9: =COUNTIF(Todos!B2:B1586,D9) -> 1
A10: deporte | B10: =COUNTIF(Todos!C2:C1586,A10) -> 115 | D10: Acceso ribereño | E10: =COUNTIF(Todos!B2:B1586,D10) -> 1
A11: educacion | B11: =COUNTIF(Todos!C2:C1586,A11) -> 34 | D11: Adiestramiento canino | E11: =COUNTIF(Todos!B2:B1586,D11) -> 1
A12: finanzas | B12: =COUNTIF(Todos!C2:C1586,A12) -> 104 | D12: Agencia de turismo | E12: =COUNTIF(Todos!B2:B1586,D12) -> 1
A13: gastronomia | B13: =COUNTIF(Todos!C2:C1586,A13) -> 302 | D13: Agencia de viajes | E13: =COUNTIF(Todos!B2:B1586,D13) -> 13
A14: mascotas | B14: =COUNTIF(Todos!C2:C1586,A14) -> 17 | D14: Agencia de viajes / Turismo | E14: =COUNTIF(Todos!B2:B1586,D14) -> 1
A15: naturaleza | B15: =COUNTIF(Todos!C2:C1586,A15) -> 27 | D15: Alarmas / Seguridad | E15: =COUNTIF(Todos!B2:B1586,D15) -> 1
A16: patrimonio | B16: =COUNTIF(Todos!C2:C1586,A16) -> 37 | D16: Alimentos balanceados | E16: =COUNTIF(Todos!B2:B1586,D16) -> 1
A17: salud | B17: =COUNTIF(Todos!C2:C1586,A17) -> 177 | D17: Almacén | E17: =COUNTIF(Todos!B2:B1586,D17) -> 1
A18: servicios_publicos | B18: =COUNTIF(Todos!C2:C1586,A18) -> 22 | D18: Almacén / Autoservicio | E18: =COUNTIF(Todos!B2:B1586,D18) -> 2
A19: transporte | B19: =COUNTIF(Todos!C2:C1586,A19) -> 177 | D19: Almacén / Verdulería | E19: =COUNTIF(Todos!B2:B1586,D19) -> 1
D20: Almacén de barrio | E20: =COUNTIF(Todos!B2:B1586,D20) -> 2
D21: Almacén gourmet / Panadería | E21: =COUNTIF(Todos!B2:B1586,D21) -> 1
D22: Almacén y Rotisería de Barrio | E22: =COUNTIF(Todos!B2:B1586,D22) -> 1
D23: Alojamiento | E23: =COUNTIF(Todos!B2:B1586,D23) -> 2
D24: Alojamiento Genérico | E24: =COUNTIF(Todos!B2:B1586,D24) -> 2
D25: Alojamiento/Bungalows | E25: =COUNTIF(Todos!B2:B1586,D25) -> 1
D26: Alojamiento/Cabañas | E26: =COUNTIF(Todos!B2:B1586,D26) -> 1
D27: Ambulancias | E27: =COUNTIF(Todos!B2:B1586,D27) -> 1
D28: Apart Hotel | E28: =COUNTIF(Todos!B2:B1586,D28) -> 2
D29: Arquitectura | E29: =COUNTIF(Todos!B2:B1586,D29) -> 1
D30: Arquitectura / Ingeniería | E30: =COUNTIF(Todos!B2:B1586,D30) -> 1
D31: Arroyo | E31: =COUNTIF(Todos!B2:B1586,D31) -> 3
D32: Artes marciales | E32: =COUNTIF(Todos!B2:B1586,D32) -> 1
D33: Artes marciales / Taekwondo | E33: =COUNTIF(Todos!B2:B1586,D33) -> 2
D34: Asociación civil | E34: =COUNTIF(Todos!B2:B1586,D34) -> 1
D35: Auditorio / Centro cultural | E35: =COUNTIF(Todos!B2:B1586,D35) -> 1
D36: Autoservicio | E36: =COUNTIF(Todos!B2:B1586,D36) -> 2
D37: Autoservicio / Maxikiosco 24hs | E37: =COUNTIF(Todos!B2:B1586,D37) -> 1
D38: Autoservicio / Supermercado | E38: =COUNTIF(Todos!B2:B1586,D38) -> 1
D39: Banco / Cajero | E39: =COUNTIF(Todos!B2:B1586,D39) -> 8
D40: Bar | E40: =COUNTIF(Todos!B2:B1586,D40) -> 16
D41: Bar / Hamburguesería | E41: =COUNTIF(Todos!B2:B1586,D41) -> 1
D42: Bar / Pub | E42: =COUNTIF(Todos!B2:B1586,D42) -> 1
D43: Bar / Salón de Eventos | E43: =COUNTIF(Todos!B2:B1586,D43) -> 1
D44: Bar Rooftop | E44: =COUNTIF(Todos!B2:B1586,D44) -> 1
D45: Bar and Grill | E45: =COUNTIF(Todos!B2:B1586,D45) -> 1
D46: Barbería | E46: =COUNTIF(Todos!B2:B1586,D46) -> 16
D47: Barrio Privado | E47: =COUNTIF(Todos!B2:B1586,D47) -> 1
D48: Bazar | E48: =COUNTIF(Todos!B2:B1586,D48) -> 1
D49: Bazar / Hogar y limpieza | E49: =COUNTIF(Todos!B2:B1586,D49) -> 1
D50: Bazar / Juguetería | E50: =COUNTIF(Todos!B2:B1586,D50) -> 1
D51: Bazar / Regalería | E51: =COUNTIF(Todos!B2:B1586,D51) -> 2
D52: Bazar y regalería | E52: =COUNTIF(Todos!B2:B1586,D52) -> 1
D53: Bazar/Regalería | E53: =COUNTIF(Todos!B2:B1586,D53) -> 1
D54: Beer Garden Costanera | E54: =COUNTIF(Todos!B2:B1586,D54) -> 1
D55: Biblioteca | E55: =COUNTIF(Todos!B2:B1586,D55) -> 1
D56: Bicicletería | E56: =COUNTIF(Todos!B2:B1586,D56) -> 8
D57: Bijouterie / Accesorios | E57: =COUNTIF(Todos!B2:B1586,D57) -> 1
D58: Boliche / Discoteca | E58: =COUNTIF(Todos!B2:B1586,D58) -> 2
D59: Buffet | E59: =COUNTIF(Todos!B2:B1586,D59) -> 1
D60: Buffet / Cafetería | E60: =COUNTIF(Todos!B2:B1586,D60) -> 1
D61: Buffet / Restaurante | E61: =COUNTIF(Todos!B2:B1586,D61) -> 1
D62: Buffet / Rotisería | E62: =COUNTIF(Todos!B2:B1586,D62) -> 1
D63: Cabañas | E63: =COUNTIF(Todos!B2:B1586,D63) -> 2
D64: Cafetería | E64: =COUNTIF(Todos!B2:B1586,D64) -> 8
D65: Cafetería / Confitería | E65: =COUNTIF(Todos!B2:B1586,D65) -> 1
D66: Cafetería / Restó | E66: =COUNTIF(Todos!B2:B1586,D66) -> 1
D67: Cafetería sin TACC | E67: =COUNTIF(Todos!B2:B1586,D67) -> 1
D68: Café Restó | E68: =COUNTIF(Todos!B2:B1586,D68) -> 2
D69: Calzado | E69: =COUNTIF(Todos!B2:B1586,D69) -> 6
D70: Calzado deportivo | E70: =COUNTIF(Todos!B2:B1586,D70) -> 1
D71: Cardiología | E71: =COUNTIF(Todos!B2:B1586,D71) -> 2
D72: Cardiología / Rehabilitación | E72: =COUNTIF(Todos!B2:B1586,D72) -> 1
D73: Carnicería | E73: =COUNTIF(Todos!B2:B1586,D73) -> 4
D74: Carnicería / Fiambrería | E74: =COUNTIF(Todos!B2:B1586,D74) -> 1
D75: Celulares | E75: =COUNTIF(Todos!B2:B1586,D75) -> 3
D76: Centro comercial | E76: =COUNTIF(Todos!B2:B1586,D76) -> 1
D77: Centro cultural | E77: =COUNTIF(Todos!B2:B1586,D77) -> 2
D78: Centro de Educación Física / Estadio | E78: =COUNTIF(Todos!B2:B1586,D78) -> 1
D79: Centro de Salud | E79: =COUNTIF(Todos!B2:B1586,D79) -> 2
D80: Centro de diagnóstico por imágenes | E80: =COUNTIF(Todos!B2:B1586,D80) -> 6
D81: Centro de estética | E81: =COUNTIF(Todos!B2:B1586,D81) -> 14
D82: Centro de estética / Salón de uñas | E82: =COUNTIF(Todos!B2:B1586,D82) -> 2
D83: Centro médico / Maternidad | E83: =COUNTIF(Todos!B2:B1586,D83) -> 1
D84: Cerrajería | E84: =COUNTIF(Todos!B2:B1586,D84) -> 10
D85: Cerrajería automotor | E85: =COUNTIF(Todos!B2:B1586,D85) -> 1
D86: Cervecería | E86: =COUNTIF(Todos!B2:B1586,D86) -> 3
D87: Cervecería artesanal | E87: =COUNTIF(Todos!B2:B1586,D87) -> 4
D88: Chapa y pintura | E88: =COUNTIF(Todos!B2:B1586,D88) -> 8
D89: Club deportivo | E89: =COUNTIF(Todos!B2:B1586,D89) -> 8
D90: Club náutico y social | E90: =COUNTIF(Todos!B2:B1586,D90) -> 1
D91: Club social y deportivo | E91: =COUNTIF(Todos!B2:B1586,D91) -> 5
D92: Clínica | E92: =COUNTIF(Todos!B2:B1586,D92) -> 5
D93: Clínica médica | E93: =COUNTIF(Todos!B2:B1586,D93) -> 1
D94: Clínica médica / Oftalmología | E94: =COUNTIF(Todos!B2:B1586,D94) -> 1
D95: Colchonería | E95: =COUNTIF(Todos!B2:B1586,D95) -> 4
D96: Colegio católico | E96: =COUNTIF(Todos!B2:B1586,D96) -> 1
D97: Colegio profesional | E97: =COUNTIF(Todos!B2:B1586,D97) -> 1
D98: Comida China / Wok | E98: =COUNTIF(Todos!B2:B1586,D98) -> 1
D99: Comida Rápida | E99: =COUNTIF(Todos!B2:B1586,D99) -> 1
D100: Comisaría | E100: =COUNTIF(Todos!B2:B1586,D100) -> 4
D101: Comisaría especializada | E101: =COUNTIF(Todos!B2:B1586,D101) -> 1
D102: Compañía de seguros | E102: =COUNTIF(Todos!B2:B1586,D102) -> 2
...

Sheet Log Auditoría
A1: Metodología: comparación masiva contra base maestra de Google Places (batch por categoría+zona), matching automático, búsqueda individual solo para casos sin resolver.
A3: Grupos completados | B3: Filas | C3: Consultas usadas | D3: Ratio filas/consulta | E3: Fecha
A4: mascotas | B4: 17 | C4: 6 | D4: 2.8 | E4: 16/07/2026
A5: comercios (10 registros con verificación débil upgradeados; 83 restantes ya tenían verificación externa previa) | B5: 10 | C5: 10 | D5: 1.0 | E5: 16/07/2026
A6: patrimonio + naturaleza (6 registros débiles upgradeados de 17 totales) | B6: 6 | C6: 6 | D6: 1.0 | E6: 16/07/2026
A7: deporte + alojamiento + finanzas/compras (18 registros débiles + 1 dudoso resuelto) | B7: 19 | C7: 13 | D7: 1.5 | E7: 16/07/2026
A8: belleza (Tanda 1 - proceso de verificación rigurosa fila por fila iniciado 17/07/2026): 10 registros verificados vía Google Places API + fuentes cruzadas | B8: 10 | C8: 11 | D8: 0.9 | E8: 17/07/2026
A11: Grupos pendientes (orden top-to-bottom de la planilla) | B11: Filas totales | C11: Sin auditar (Estado Auditoría Lote = NaN)
A12: comercios | B12: 93 | C12: 0
A13: patrimonio | B13: 37 | C13: revisar
A14: naturaleza | B14: 27 | C14: revisar
A15: transporte | B15: 177 | C15: revisar
A16: deporte | B16: 115 | C16: revisar
A17: alojamiento | B17: 32 | C17: revisar
A18: finanzas | B18: 104 | C18: revisar
A19: compras | B19: 265 | C19: revisar
A20: salud | B20: 177 | C20: revisar
A21: gastronomia | B21: 302 | C21: revisar
A22: belleza | B22: 99 | C22: revisar
A23: servicios_publicos | B23: 22 | C23: revisar
A24: educacion | B24: 34 | C24: revisar
A25: oficios_tecnicos | B25: 83 | C25: revisar
A27: Comercios detectados en Google Places que NO están en la planilla (candidatos a alta) | B27: Dirección | C27: Rubro
A28: VipVet Clinica Veterinaria | B28: 9 de Julio 1427 | C28: Veterinaria
A29: NORTE - Pet shop | B29: Blvd. Hipólito Yrigoyen 611 | C29: Pet shop / forrajería
A30: Mascota Urbana Pet Shop | B30: Gral. Galarza 627 | C30: Pet shop
A31: PuppyDog PetShop | B31: República de Chile 332 | C31: Pet shop
A32: San José Petshop | B32: Posadas 1582 | C32: Pet shop
A33: Agroveterinaria 9 de Julio (2da ficha) | B33: 9 de Julio 1016 | C33: Veterinaria - posible duplicado en Google Maps de la fila 112
A35: Inconsistencias detectadas (no resueltas, requieren decisión del cliente)
A36: Fila 112 - Agroveterinaria 9 de Julio de Argacha Hirinson: existen DOS fichas de Google Places en la misma dirección (9 de Julio 1016) con teléfonos distintos (+54 3442 42-3827 vs +54 3442 42-7801 de la planilla). Podría ser el mismo comercio con doble alta en Google, o dos negocios distintos en la misma dirección.
